jenkins_mcp_server/__init__.py
jenkins_mcp_server/__main__.py
jenkins_mcp_server/exceptions.py
jenkins_mcp_server/models.py
jenkins_mcp_server/server.py
jenkins_mcp_server/handlers/__init__.py
jenkins_mcp_server/handlers/base_handler.py
jenkins_mcp_server/handlers/build_handler.py
jenkins_mcp_server/handlers/job_handler.py
jenkins_mcp_server/utils/__init__.py
jenkins_mcp_server/utils/cache.py
jenkins_mcp_server/utils/connection_pool.py
jenkins_mcp_server/utils/logging_helper.py
jenkins_mcp_server/utils/path_utils.py
jenkins_mcp_server/utils/retry.py
jenkins_mcp_server/utils/validation.py
jenkins_mcp_community-1.0.0.dist-info/METADATA
jenkins_mcp_community-1.0.0.dist-info/WHEEL
jenkins_mcp_community-1.0.0.dist-info/entry_points.txt
jenkins_mcp_community-1.0.0.dist-info/licenses/LICENSE
jenkins_mcp_community-1.0.0.dist-info/RECORD
