Metadata-Version: 2.4
Name: jenkins-mcp-community
Version: 1.0.0
Summary: Community Edition Model Context Protocol (MCP) server for Jenkins CI/CD integration
Project-URL: Homepage, https://github.com/jenkins-mcp-community/jenkins-mcp-server
Project-URL: Documentation, https://github.com/jenkins-mcp-community/jenkins-mcp-server#readme
Project-URL: Repository, https://github.com/jenkins-mcp-community/jenkins-mcp-server
Project-URL: Bug Tracker, https://github.com/jenkins-mcp-community/jenkins-mcp-server/issues
Project-URL: Changelog, https://github.com/jenkins-mcp-community/jenkins-mcp-server/blob/main/CHANGELOG.md
Author-email: Jenkins MCP Community <jenkins-mcp-community@example.com>
Maintainer-email: Jenkins MCP Community <jenkins-mcp-community@example.com>
License: MIT
License-File: LICENSE
Keywords: ai,automation,cicd,devops,jenkins,mcp,model-context-protocol
Classifier: Development Status :: 5 - Production/Stable
Classifier: Environment :: Console
Classifier: Framework :: AsyncIO
Classifier: Intended Audience :: Developers
Classifier: Intended Audience :: System Administrators
Classifier: License :: OSI Approved :: MIT License
Classifier: Operating System :: OS Independent
Classifier: Programming Language :: Python
Classifier: Programming Language :: Python :: 3
Classifier: Programming Language :: Python :: 3.10
Classifier: Programming Language :: Python :: 3.11
Classifier: Programming Language :: Python :: 3.12
Classifier: Programming Language :: Python :: 3.13
Classifier: Topic :: Internet :: WWW/HTTP :: HTTP Servers
Classifier: Topic :: Scientific/Engineering :: Artificial Intelligence
Classifier: Topic :: Software Development :: Libraries :: Python Modules
Classifier: Topic :: System :: Systems Administration
Requires-Python: >=3.10
Requires-Dist: cachetools>=5.3.0
Requires-Dist: httpx>=0.27.0
Requires-Dist: jenkinsapi>=0.3.14
Requires-Dist: loguru>=0.7.0
Requires-Dist: mcp[cli]>=1.6.0
Requires-Dist: pydantic>=2.10.6
Requires-Dist: python-dotenv>=1.0.1
Requires-Dist: python-jenkins>=1.8.0
Requires-Dist: tenacity>=8.2.0
Provides-Extra: dev
Requires-Dist: mypy>=1.8.0; extra == 'dev'
Requires-Dist: pre-commit>=4.1.0; extra == 'dev'
Requires-Dist: pytest-asyncio>=0.23.0; extra == 'dev'
Requires-Dist: pytest-cov>=4.1.0; extra == 'dev'
Requires-Dist: pytest-mock>=3.12.0; extra == 'dev'
Requires-Dist: pytest>=8.0.0; extra == 'dev'
Requires-Dist: ruff>=0.9.7; extra == 'dev'
Provides-Extra: test
Requires-Dist: pytest-asyncio>=0.23.0; extra == 'test'
Requires-Dist: pytest-cov>=4.1.0; extra == 'test'
Requires-Dist: pytest-mock>=3.12.0; extra == 'test'
Requires-Dist: pytest>=8.0.0; extra == 'test'
Requires-Dist: responses>=0.24.0; extra == 'test'
